ignore/__init__.py
ignore/ignore.py
python_gitignore_generator-0.0.3.dist-info/METADATA
python_gitignore_generator-0.0.3.dist-info/WHEEL
python_gitignore_generator-0.0.3.dist-info/top_level.txt
python_gitignore_generator-0.0.3.dist-info/RECORD
